{
  "admin": "",
  "adminPassword": "",
  "allowCsvDownload": true,
  "baseUrl": "",
  "certPassphrase": "",
  "certPath": "",
  "cookieName": "sqlpad.sid",
  "cookieSecret": "secret-used-to-sign-cookies-please-set-and-make-strong",
  "dbPath": "",
  "debug": false,
  "disableUserpassAuth": false,
  "editorWordWrap": false,
  "googleClientId": "",
  "googleClientSecret": "",
  "httpsPort": 443,
  "ip": "0.0.0.0",
  "keyPath": "",
  "passphrase": "At least the sensitive bits won't be plain text?",
  "port": 80,
  "publicUrl": "",
  "queryResultMaxRows": 50000,
  "samlAuthContext": "",
  "samlCallbackUrl": "",
  "samlCert": "",
  "samlEntryPoint": "",
  "samlIssuer": "",
  "sessionMinutes": 60,
  "slackWebhook": "",
  "smtpFrom": "",
  "smtpHost": "",
  "smtpPassword": "",
  "smtpPort": "",
  "smtpSecure": true,
  "smtpUser": "",
  "systemdSocket": false,
  "tableChartLinksRequireAuth": true,
  "timeoutSeconds": 300,
  "whitelistedDomains": ""
}
